MANIFEST.in
Makefile
README
setup.cfg
setup.py
twconsole
tiddlywebplugins/__init__.py
tiddlywebplugins.console.egg-info/PKG-INFO
tiddlywebplugins.console.egg-info/SOURCES.txt
tiddlywebplugins.console.egg-info/dependency_links.txt
tiddlywebplugins.console.egg-info/namespace_packages.txt
tiddlywebplugins.console.egg-info/not-zip-safe
tiddlywebplugins.console.egg-info/requires.txt
tiddlywebplugins.console.egg-info/top_level.txt
tiddlywebplugins/console/__init__.py
tiddlywebplugins/console/config.py
tiddlywebplugins/console/instance.py
tiddlywebplugins/console/resources/store/bags/console/description
tiddlywebplugins/console/resources/store/bags/console/policy
tiddlywebplugins/console/resources/store/bags/console/tiddlers/chrjs.js/1
tiddlywebplugins/console/resources/store/bags/console/tiddlers/config.js/1
tiddlywebplugins/console/resources/store/bags/console/tiddlers/index.html/1
tiddlywebplugins/console/resources/store/bags/console/tiddlers/jquery-json.min.js/1
tiddlywebplugins/console/resources/store/bags/console/tiddlers/jquery.min.js/1
tiddlywebplugins/console/resources/store/bags/console/tiddlers/main.css/1
tiddlywebplugins/console/resources/store/bags/console/tiddlers/main.js/1
tiddlywebplugins/console/resources/store/bags/console/tiddlers/util.js/1