Metadata-Version: 1.0
Name: tiddlywebplugins.console
Version: 0.3.0
Summary: TiddlyWeb explorer
Home-page: http://pypi.python.org/pypi/tiddlywebplugins.console
Author: FND
Author-email: FNDo@gmx.net
License: UNKNOWN
Platform: Posix; MacOS X; Windows
